lammps_logfile/File.py
lammps_logfile/__init__.py
lammps_logfile/cmd_interface.py
lammps_logfile/reader.py
lammps_logfile/utils.py
lammps_logfile-1.1.3.dist-info/licenses/LICENSE
tests/__init__.py
tests/test_File.py
tests/test_reader.py
tests/test_thermo_style_multi.py
lammps_logfile-1.1.3.dist-info/METADATA
lammps_logfile-1.1.3.dist-info/WHEEL
lammps_logfile-1.1.3.dist-info/entry_points.txt
lammps_logfile-1.1.3.dist-info/top_level.txt
lammps_logfile-1.1.3.dist-info/RECORD
